emailer_inao/__init__.py
emailer_inao/cli.py
emailer_inao/core/__init__.py
emailer_inao/core/campaign_manager.py
emailer_inao/core/email_sender.py
emailer_inao/core/picture_generator.py
emailer_inao/utils/__init__.py
emailer_inao/utils/credential_manager.py
emailer_inao/utils/document_processor.py
emailer_inao/utils/email_formatter.py
emailer_inao/utils/global_config.py
emailer_inao/utils/logger.py
emailer_inao/utils/smtp_helper.py
emailer_inao/utils/template_processor.py
emailer_inao/utils/validators.py
emailer_inao-4.0.1.dist-info/METADATA
emailer_inao-4.0.1.dist-info/WHEEL
emailer_inao-4.0.1.dist-info/entry_points.txt
emailer_inao-4.0.1.dist-info/top_level.txt
emailer_inao-4.0.1.dist-info/RECORD
